jinja2cli/__init__.py
jinja2cli/cli.py
jinja2_cli_tddschn-0.9.2.dist-info/LICENSE
jinja2_cli_tddschn-0.9.2.dist-info/METADATA
jinja2_cli_tddschn-0.9.2.dist-info/WHEEL
jinja2_cli_tddschn-0.9.2.dist-info/entry_points.txt
jinja2_cli_tddschn-0.9.2.dist-info/RECORD
