Metadata-Version: 2.1
Name: jinja2-cli-tddschn
Version: 0.9.2
Summary: A CLI interface to Jinja2
Home-page: https://github.com/tddschn/jinja2-cli-tddschn
License: BSD-2-Clause
Keywords: jinja2,jinja,templating
Author: Matt Robenolt
Author-email: matt@ydekproductions.com
Requires-Python: >=3.12,<4.0
Classifier: License :: OSI Approved :: BSD License
Classifier: Programming Language :: Python :: 3
Classifier: Programming Language :: Python :: 3.12
Classifier: Topic :: Utilities
Provides-Extra: hjson
Provides-Extra: json5
Provides-Extra: toml
Provides-Extra: xml
Provides-Extra: yaml
Requires-Dist: jinja2 (>=3.1.2,<4.0.0)
Project-URL: Bug Tracker, https://github.com/tddschn/jinja2-cli-tddschn/issues
Project-URL: Repository, https://github.com/tddschn/jinja2-cli-tddschn
